sshtunnel.py
sshtunnel-0.3.2.dist-info/LICENSE
sshtunnel-0.3.2.dist-info/METADATA
sshtunnel-0.3.2.dist-info/WHEEL
sshtunnel-0.3.2.dist-info/entry_points.txt
sshtunnel-0.3.2.dist-info/top_level.txt
sshtunnel-0.3.2.dist-info/RECORD
