Metadata-Version: 2.1
Name: sshtunnel
Version: 0.3.2
Summary: Pure python SSH tunnels
Home-page: https://github.com/pahaz/sshtunnel
Author: Pahaz White
Author-email: pahaz.white@gmail.com
License: MIT
Download-URL: https://pypi.python.org/packages/source/s/sshtunnel/sshtunnel-0.3.2.zip
Keywords: ssh tunnel paramiko proxy tcp-forward
Platform: unix
Platform: macos
Platform: windows
Classifier: Development Status :: 3 - Alpha
Classifier: Intended Audience :: Developers
Classifier: Topic :: Software Development :: Build Tools
Classifier: License :: OSI Approved :: MIT License
Classifier: Programming Language :: Python :: 2
Classifier: Programming Language :: Python :: 2.7
Classifier: Programming Language :: Python :: 3
Classifier: Programming Language :: Python :: 3.4
Classifier: Programming Language :: Python :: 3.5
Classifier: Programming Language :: Python :: 3.6
Classifier: Programming Language :: Python :: 3.7
Classifier: Programming Language :: Python :: 3.8
Requires-Dist: paramiko (>=1.15.2)
Provides-Extra: build_sphinx
Requires-Dist: sphinx ; extra == 'build_sphinx'
Requires-Dist: sphinxcontrib-napoleon ; extra == 'build_sphinx'
Provides-Extra: dev
Requires-Dist: check-manifest ; extra == 'dev'
Provides-Extra: test
Requires-Dist: tox (>=1.8.1) ; extra == 'test'
